matching_algorithms/__init__.py
matching_algorithms/main.py
matching_algorithms-0.1.0.dist-info/LICENSE
matching_algorithms-0.1.0.dist-info/METADATA
matching_algorithms-0.1.0.dist-info/WHEEL
matching_algorithms-0.1.0.dist-info/top_level.txt
matching_algorithms-0.1.0.dist-info/RECORD
