Metadata-Version: 2.1
Name: matching-algorithms
Version: 0.1.0
Summary: This project implements a variety of matching algorithms, including the Deferred Acceptance algorithm, the Boston Mechanism, the Top Trading Cycles (TTC) mechanism, and several linear programming approaches. These algorithms are widely applicable in various domains such as school admissions, job assignments, and resource allocation problems. Their effectiveness in creating stable and efficient matchings makes them valuable tools in economics, computer science and operations research.
Home-page: https://github.com/Tekdirfan/Matching-Algorithms.git
Author: Irfan Tekdir
Author-email: irfan.tekdir@gmail.com
Classifier: Intended Audience :: Science/Research
Classifier: Programming Language :: Python :: 3
Classifier: License :: OSI Approved :: MIT License
Classifier: Operating System :: OS Independent
Requires-Python: >=3.6
License-File: LICENSE
Requires-Dist: numpy
Requires-Dist: pulp
